guavahash.cpython-311-darwin.so
guavahash-1.0.2.dist-info/RECORD
guavahash-1.0.2.dist-info/WHEEL
guavahash-1.0.2.dist-info/top_level.txt
guavahash-1.0.2.dist-info/METADATA
guavahash-1.0.2.dist-info/licenses/LICENSE.txt
