Metadata-Version: 2.4
Name: guavahash
Version: 1.0.2
Summary: Google's Guava consistent hashing implementation
Author-email: igorcoding <igorcoding@gmail.com>
License-Expression: MIT
Project-URL: Homepage, https://github.com/igorcoding/guavahash
Project-URL: Repository, https://github.com/igorcoding/guavahash
Project-URL: Download, https://github.com/igorcoding/guavahash/tarball/v0.4
Keywords: guava,consistent,hashing,hash,digest
Classifier: Development Status :: 5 - Production/Stable
Classifier: Intended Audience :: Developers
Classifier: Topic :: Software Development :: Libraries
Classifier: Programming Language :: Python :: 3.10
Classifier: Programming Language :: Python :: 3.11
Classifier: Programming Language :: Python :: 3.12
Classifier: Programming Language :: Python :: 3.13
Requires-Python: >=3.10
License-File: LICENSE.txt
Provides-Extra: test
Requires-Dist: pytest>=3.0; extra == "test"
Dynamic: license-file
